{"cameraMode":{"drawMode":0,"name":"Shaded","section":"Shading Mode"},"sceneLighting":true,"audioPlay":false,"sceneViewState":{"showFog":true,"showMaterialUpdate":false,"showSkybox":true,"showFlares":true,"showImageEffects":true,"showParticleSystems":true},"in2DMode":false,"pivot":{"x":-261.5914611816406,"y":16.56806182861328,"z":-156.1761016845703},"rotation":{"x":-0.031596530228853229,"y":-0.968290388584137,"z":0.17023906111717225,"w":-0.18076832592487336},"size":191.50405883789063,"orthographic":false}