{"cameraMode":{"drawMode":0,"name":"Shaded","section":"Shading Mode"},"sceneLighting":true,"audioPlay":false,"sceneViewState":{"showFog":true,"showMaterialUpdate":false,"showSkybox":true,"showFlares":true,"showImageEffects":true,"showParticleSystems":true},"in2DMode":false,"pivot":{"x":-319.1357421875,"y":103.05598449707031,"z":-10.338062286376954},"rotation":{"x":0.009804117493331433,"y":0.8709675669670105,"z":0.01858062855899334,"w":-0.49129414558410647},"size":24.09095001220703,"orthographic":false}